sharejeeni
