Metadata-Version: 2.1
Name: sharejeeni
Version: 1.0.3
Summary: Download files from sharepoint site using client id , client secret and tenant id via Azure Active Directory. 
Author: Jeevan V
Author-email: jeevanvsan@gmail.com
Keywords: sharejeeni,sharepoint,sharepoint file
Classifier: Programming Language :: Python :: 3
Classifier: License :: OSI Approved :: MIT License
Classifier: Operating System :: OS Independent
License-File: LICENSE.txt
